AUTHORS
COPYING
MANIFEST.in
README.md
readme_example.py
setup.py
src/PyProxyFS.egg-info/PKG-INFO
src/PyProxyFS.egg-info/SOURCES.txt
src/PyProxyFS.egg-info/dependency_links.txt
src/PyProxyFS.egg-info/top_level.txt
src/pyproxyfs/__init__.py
src/pyproxyfs/test.py
src/pyproxyfs/testit.py