Metadata-Version: 1.0
Name: PyProxyFS
Version: 0.8
Summary: Simple filesystem abstraction
Home-page: http://github.com/nicferrier/pyproxyfs
Author: Nic Ferrier
Author-email: nic@ferrier.me.uk
License: GNU GPL v3
Download-URL: http://github.com/nicferrier/pyproxyfs/downloads
Platform: any
Classifier: Development Status :: 3 - Alpha
Classifier: Intended Audience :: Developers
Classifier: License :: OSI Approved :: GNU General Public License (GPL)
Classifier: Operating System :: OS Independent
Classifier: Programming Language :: Python
Classifier: Topic :: System :: Filesystems
